sphinx_lesson/__init__.py
sphinx_lesson/_version.py
sphinx_lesson/directives.py
sphinx_lesson/exerciselist.py
sphinx_lesson/md_transforms.py
sphinx_lesson/term_role_formatting.py
sphinx_lesson/_static/sphinx_lesson.css
sphinx_lesson/_static/term_role_formatting.css
sphinx_lesson-0.8.20.dist-info/licenses/LICENSE
sphinx_lesson-0.8.20.dist-info/WHEEL
sphinx_lesson-0.8.20.dist-info/METADATA
sphinx_lesson-0.8.20.dist-info/RECORD
