Metadata-Version: 2.4
Name: sphinx-lesson
Version: 0.8.20
Summary: Sphinx extension for CodeRefinery lessons
Keywords: sphinx-extension
Author: Richard Darst
Requires-Python: >=3.3
Classifier: License :: OSI Approved :: MIT License
Classifier: Programming Language :: Python :: 3
Classifier: Development Status :: 4 - Beta
Classifier: Framework :: Sphinx
Classifier: Framework :: Sphinx :: Extension
Classifier: Operating System :: OS Independent
License-File: LICENSE
Requires-Dist: sphinx<9
Requires-Dist: sphinx_rtd_theme
Requires-Dist: sphinx_copybutton
Requires-Dist: sphinx_minipres
Requires-Dist: sphinx_tabs
Requires-Dist: sphinx_togglebutton>=0.2.0
Requires-Dist: sphinx-autobuild
Requires-Dist: myst_nb>0.8.3
Requires-Dist: sphinx_rtd_theme_ext_color_contrast
Project-URL: Documentation, https://coderefinery.github.io/sphinx-lesson/
Project-URL: Repository, https://github.com/coderefinery/sphinx-lesson
